amxtoexcel/__init__.py
amxtoexcel-0.0.7.dist-info/LICENSE
amxtoexcel-0.0.7.dist-info/METADATA
amxtoexcel-0.0.7.dist-info/WHEEL
amxtoexcel-0.0.7.dist-info/top_level.txt
amxtoexcel-0.0.7.dist-info/RECORD
