Metadata-Version: 2.1
Name: amxtoexcel
Version: 0.0.7
Summary: amx dict list to xlsx
Home-page: https://github.com/logantv/amxtoexcel
Author: Logan Vaughn
License: UNKNOWN
Project-URL: Bug Tracker, https://github.com/logantv/amxtoexcel/issues
Platform: UNKNOWN
Classifier: Programming Language :: Python :: 3
Classifier: License :: OSI Approved :: MIT License
Classifier: Operating System :: OS Independent
Requires-Python: >=3.6
Requires-Dist: openpyxl
Requires-Dist: pandas
